{
  "_class": "symbolInstance",
  "do_objectID": "903E1EAB-8CB7-4698-AD5E-DF9CBC65C02B",
  "exportOptions": {
    "_class": "exportOptions",
    "do_objectID": "CDCCE95A-5DB3-48DA-9326-0863F79DC656",
    "exportFormats": [
      {
        "_class": "exportFormat",
        "absoluteSize": 0,
        "fileFormat": "png",
        "name": "",
        "namingScheme": 0,
        "scale": 1,
        "visibleScaleType": 0
      },
      {
        "_class": "exportFormat",
        "absoluteSize": 0,
        "fileFormat": "png",
        "name": "@2x",
        "namingScheme": 0,
        "scale": 2,
        "visibleScaleType": 0
      },
      {
        "_class": "exportFormat",
        "absoluteSize": 0,
        "fileFormat": "png",
        "name": "@3x",
        "namingScheme": 0,
        "scale": 3,
        "visibleScaleType": 0
      }
    ],
    "includedLayerIds": [
    ],
    "layerOptions": 0,
    "shouldTrim": false
  },
  "frame": {
    "_class": "rect",
    "constrainProportions": false,
    "do_objectID": "C917AB1F-9312-4A0B-B820-FD350BAFDAAA",
    "height": 40,
    "width": 125,
    "x": 0,
    "y": 72
  },
  "horizontalSpacing": 0,
  "isFlippedHorizontal": false,
  "isFlippedVertical": false,
  "isLocked": false,
  "isVisible": true,
  "layerListExpandedType": 0,
  "name": "input / timeEachBound40",
  "nameIsFixed": true,
  "overrideValues": [
    {
      "_class": "overrideValue",
      "do_objectID": "C337076A-FABC-4CCB-ACC1-1B02A681A47E",
      "overrideName": "90DB8AED-0E85-42A8-931E-A05A5F9938F1_stringValue",
      "value": "오전"
    }
  ],
  "resizingConstraint": 45,
  "resizingType": 0,
  "rotation": 0,
  "scale": 1,
  "shouldBreakMaskChain": false,
  "style": {
    "_class": "style",
    "do_objectID": "CF3B4915-FE75-4ECE-B8A1-C4C2AA643A57",
    "endDecorationType": 0,
    "miterLimit": 10,
    "startDecorationType": 0
  },
  "symbolID": "5110DF8B-3D6F-401A-86FA-9978EDA0AAC4",
  "verticalSpacing": 0
}