{
  "_class": "artboard",
  "backgroundColor": {
    "_class": "color",
    "alpha": 1,
    "blue": 0.8980392156862745,
    "green": 0.8980392156862745,
    "red": 0.8980392156862745
  },
  "do_objectID": "B74040E7-C850-4013-91B4-0E3F171A580E",
  "exportOptions": {
    "_class": "exportOptions",
    "exportFormats": [
      {
        "_class": "exportFormat",
        "absoluteSize": 0,
        "fileFormat": "png",
        "name": "mdpi/",
        "namingScheme": 1,
        "scale": 1,
        "visibleScaleType": 0
      },
      {
        "_class": "exportFormat",
        "absoluteSize": 0,
        "fileFormat": "png",
        "name": "hdpi/",
        "namingScheme": 1,
        "scale": 1.5,
        "visibleScaleType": 0
      },
      {
        "_class": "exportFormat",
        "absoluteSize": 0,
        "fileFormat": "png",
        "name": "xhdpi/",
        "namingScheme": 1,
        "scale": 2,
        "visibleScaleType": 0
      },
      {
        "_class": "exportFormat",
        "absoluteSize": 0,
        "fileFormat": "png",
        "name": "xxhdpi/",
        "namingScheme": 1,
        "scale": 3,
        "visibleScaleType": 0
      },
      {
        "_class": "exportFormat",
        "absoluteSize": 0,
        "fileFormat": "png",
        "name": "xxxhdpi/",
        "namingScheme": 1,
        "scale": 4,
        "visibleScaleType": 0
      }
    ],
    "includedLayerIds": [
    ],
    "layerOptions": 0,
    "shouldTrim": false
  },
  "frame": {
    "_class": "rect",
    "constrainProportions": false,
    "height": 624,
    "width": 832,
    "x": -437,
    "y": 344
  },
  "hasBackgroundColor": true,
  "hasClickThrough": false,
  "horizontalRulerData": {
    "_class": "rulerData",
    "base": 0,
    "guides": [
    ]
  },
  "includeBackgroundColorInExport": true,
  "includeInCloudUpload": true,
  "isFlippedHorizontal": false,
  "isFlippedVertical": false,
  "isFlowHome": false,
  "isLocked": false,
  "isVisible": true,
  "layerListExpandedType": 0,
  "layers": [
    {
      "class": "symbolInstance",
      "id": "36C83343-E60A-4390-9DCF-F17BA9064034"
    },
    {
      "class": "symbolInstance",
      "id": "6CB7C6A3-7CDE-4FA6-826C-0ED01C43EB33"
    },
    {
      "class": "symbolInstance",
      "id": "80C156FC-EC83-4735-AF94-E9C5796972DE"
    },
    {
      "class": "symbolInstance",
      "id": "AF4EB4BC-B93A-48CD-986D-AF6B3BF3B907"
    },
    {
      "class": "symbolInstance",
      "id": "72C4388A-5F70-4D35-8D94-6351C4DE6226"
    },
    {
      "class": "symbolInstance",
      "id": "85521554-492A-4CD3-B932-005F25D9E756"
    },
    {
      "class": "symbolInstance",
      "id": "EE75462D-7E33-49DE-9446-C28975BCC0F3"
    },
    {
      "class": "symbolInstance",
      "id": "ACA44DB5-C309-42E1-8B85-77D9A5213ABF"
    },
    {
      "class": "symbolInstance",
      "id": "17921CE7-C303-40F4-8311-58EFB6DBECD1"
    },
    {
      "class": "symbolInstance",
      "id": "90C8A5C7-D2B9-4EF4-A25A-B465098B6735"
    },
    {
      "class": "symbolInstance",
      "id": "D17FFA42-6678-4864-8EB5-B6BCFDF329F9"
    },
    {
      "class": "symbolInstance",
      "id": "ED1658B4-E72F-4BA8-92B7-47BD4DD93941"
    },
    {
      "class": "symbolInstance",
      "id": "FB0A5B73-9AF9-48C3-A20A-2CB3D2B40E8C"
    },
    {
      "class": "symbolInstance",
      "id": "94470AFE-C8AB-4129-A2EF-40A7A618147D"
    },
    {
      "class": "symbolInstance",
      "id": "0AAE26D0-DE75-4D7F-9763-A5361CA19E4D"
    },
    {
      "class": "symbolInstance",
      "id": "869CC576-3539-4EC1-BC64-A1F1304FCE2C"
    },
    {
      "class": "symbolInstance",
      "id": "451D045C-50D1-4E29-BFEC-9C084E07F43F"
    },
    {
      "class": "symbolInstance",
      "id": "F3F374D6-0640-4BAA-AF73-951D106C47F7"
    },
    {
      "class": "symbolInstance",
      "id": "2798FAEF-0FF5-4E21-A7E1-CB548A68C8FA"
    }
  ],
  "name": "btns",
  "nameIsFixed": true,
  "resizesContent": false,
  "resizingConstraint": 63,
  "resizingType": 0,
  "rotation": 0,
  "shouldBreakMaskChain": true,
  "style": {
    "_class": "style",
    "endDecorationType": 0,
    "fills": [
      {
        "_class": "fill",
        "color": {
          "_class": "color",
          "alpha": 1,
          "blue": 1,
          "green": 1,
          "red": 1
        },
        "fillType": 0,
        "isEnabled": true,
        "noiseIndex": 0,
        "noiseIntensity": 0,
        "patternFillType": 1,
        "patternTileScale": 1
      }
    ],
    "miterLimit": 10,
    "startDecorationType": 0
  },
  "verticalRulerData": {
    "_class": "rulerData",
    "base": 0,
    "guides": [
    ]
  }
}